altpip/__init__.py
altpip/_version.py
altpip/core.py
altpip/generator.py
altpip-0.2.25.dist-info/LICENSE
altpip-0.2.25.dist-info/METADATA
altpip-0.2.25.dist-info/WHEEL
altpip-0.2.25.dist-info/entry_points.txt
altpip-0.2.25.dist-info/top_level.txt
altpip-0.2.25.dist-info/RECORD
