Metadata-Version: 2.1
Name: altpip
Version: 0.2.25
Summary: AltPIP - a tool for creating projects with the required versions of libraries without using virtual environments (like venv)
Author: nesquick
Author-email: nesquary@gmail.com
License: MIT
License-File: LICENSE
Requires-Dist: tqdm
